somenzz/__init__.py
somenzz/decorators/__init__.py
somenzz/decorators/retry.py
somenzz/decorators/timeit.py
somenzz_decorators-0.2.dist-info/LICENSE
somenzz_decorators-0.2.dist-info/METADATA
somenzz_decorators-0.2.dist-info/WHEEL
somenzz_decorators-0.2.dist-info/top_level.txt
somenzz_decorators-0.2.dist-info/RECORD
