Metadata-Version: 2.1
Name: somenzz-decorators
Version: 0.2
Summary: List of useful decorators in Python.
Home-page: https://github.com/somenzz/awe-decorators
Author: somenzz
Author-email: somenzz@163.com
License: The MIT License (MIT)
